pytest_approval/__init__.py
pytest_approval/approver.toml
pytest_approval/compare.py
pytest_approval/config.py
pytest_approval/definitions.py
pytest_approval/empty_files/empty.7z
pytest_approval/empty_files/empty.7zip
pytest_approval/empty_files/empty.avif
pytest_approval/empty_files/empty.bmp
pytest_approval/empty_files/empty.bz2
pytest_approval/empty_files/empty.bzip2
pytest_approval/empty_files/empty.dds
pytest_approval/empty_files/empty.dib
pytest_approval/empty_files/empty.docx
pytest_approval/empty_files/empty.emf
pytest_approval/empty_files/empty.exif
pytest_approval/empty_files/empty.gif
pytest_approval/empty_files/empty.gz
pytest_approval/empty_files/empty.gzip
pytest_approval/empty_files/empty.heic
pytest_approval/empty_files/empty.heif
pytest_approval/empty_files/empty.ico
pytest_approval/empty_files/empty.j2c
pytest_approval/empty_files/empty.jfif
pytest_approval/empty_files/empty.jp2
pytest_approval/empty_files/empty.jpc
pytest_approval/empty_files/empty.jpe
pytest_approval/empty_files/empty.jpeg
pytest_approval/empty_files/empty.jpg
pytest_approval/empty_files/empty.jxr
pytest_approval/empty_files/empty.nupkg
pytest_approval/empty_files/empty.odp
pytest_approval/empty_files/empty.ods
pytest_approval/empty_files/empty.odt
pytest_approval/empty_files/empty.pbm
pytest_approval/empty_files/empty.pcx
pytest_approval/empty_files/empty.pdf
pytest_approval/empty_files/empty.pgm
pytest_approval/empty_files/empty.png
pytest_approval/empty_files/empty.ppm
pytest_approval/empty_files/empty.pptx
pytest_approval/empty_files/empty.rle
pytest_approval/empty_files/empty.rtf
pytest_approval/empty_files/empty.tar
pytest_approval/empty_files/empty.tga
pytest_approval/empty_files/empty.tif
pytest_approval/empty_files/empty.tiff
pytest_approval/empty_files/empty.wdp
pytest_approval/empty_files/empty.webp
pytest_approval/empty_files/empty.wmp
pytest_approval/empty_files/empty.xlsx
pytest_approval/empty_files/empty.xz
pytest_approval/empty_files/empty.zip
pytest_approval-0.3.0.dist-info/licenses/COPYING
pytest_approval-0.3.0.dist-info/licenses/COPYING.LESSER
pytest_approval-0.3.0.dist-info/WHEEL
pytest_approval-0.3.0.dist-info/entry_points.txt
pytest_approval-0.3.0.dist-info/METADATA
pytest_approval-0.3.0.dist-info/RECORD
