Metadata-Version: 2.4
Name: pytest-approval
Version: 0.3.0
Summary: A simple approval test library utilizing external diff programs such as PyCharm and Visual Studio Code to compare approved and received output.
Author: HeiGIT ohsome team
Author-email: HeiGIT ohsome team <ohsome@heigit.org>
License-Expression: LGPL-3.0-only
License-File: COPYING
License-File: COPYING.LESSER
Classifier: Framework :: Pytest
Classifier: Intended Audience :: Developers
Classifier: License :: OSI Approved :: GNU Lesser General Public License v3 (LGPLv3)
Classifier: Programming Language :: Python :: 3 :: Only
Classifier: Programming Language :: Python :: 3.11
Classifier: Programming Language :: Python :: 3.12
Classifier: Programming Language :: Python :: 3.13
Classifier: Programming Language :: Python :: 3.14
Classifier: Topic :: Software Development :: Libraries :: Python Modules
Classifier: Topic :: Software Development :: Testing
Requires-Dist: pytest>=8.3.5
Requires-Dist: numpy>=2.3.1 ; extra == 'image'
Requires-Dist: pillow>=11.3.0 ; extra == 'image'
Requires-Python: >=3.11, <3.15
Project-URL: Documentation, https://github.com/GIScience/pytest-approval/blob/main/README.md
Project-URL: Homepage, https://ohsome.org/
Project-URL: Issues, https://github.com/GISciene/pytest-approval/issues
Project-URL: Repository, https://github.com/GIScience/pytest-approval
Provides-Extra: image
